{"title":"Correction: Mapping the dynamics of force transduction at cell–cell junctions of epithelial clusters","author":[{"surname":"Ng","given-names":"Mei Rosa"},{"surname":"Besser","given-names":"Achim"},{"surname":"Brugge","given-names":"Joan S"},{"surname":"Danuser","given-names":"Gaudenz"}],"abstract":null,"identifier":[{"type":"publisher-id","id":"06656"},{"type":"doi","id":"10.7554/eLife.06656"}],"date":{"day":"02","month":"02","year":"2015"},"license":"http://creativecommons.org/licenses/by/4.0/","path":"06656","entryfile":"elife-06656-v1.xml","files":[]}