{"title":"Global mapping of highly pathogenic avian influenza H5N1 and H5Nx clade 2.3.4.4 viruses with spatial cross-validation","author":[{"surname":"Dhingra","given-names":"Madhur S"},{"surname":"Artois","given-names":"Jean"},{"surname":"Robinson","given-names":"Timothy P"},{"surname":"Linard","given-names":"Catherine"},{"surname":"Chaiban","given-names":"Celia"},{"surname":"Xenarios","given-names":"Ioannis"},{"surname":"Engler","given-names":"Robin"},{"surname":"Liechti","given-names":"Robin"},{"surname":"Kuznetsov","given-names":"Dmitri"},{"surname":"Xiao","given-names":"Xiangming"},{"surname":"Dobschuetz","given-names":"Sophie Von"},{"surname":"Claes","given-names":"Filip"},{"surname":"Newman","given-names":"Scott H"},{"surname":"Dauphin","given-names":"Gwenaëlle"},{"surname":"Gilbert","given-names":"Marius"}],"abstract":"Global disease suitability models are essential tools to inform surveillance systems and enable early detection. We present the first global suitability model of highly pathogenic avian influenza (HPAI) H5N1 and demonstrate that reliable predictions can be obtained at global scale. Best predictions are obtained using spatial predictor variables describing host distributions, rather than land use or eco-climatic spatial predictor variables, with a strong association with domestic duck and extensively raised chicken densities. Our results also support a more systematic use of spatial cross-validation in large-scale disease suitability modelling compared to standard random cross-validation that can lead to unreliable measure of extrapolation accuracy. A global suitability model of the H5 clade 2.3.4.4 viruses, a group of viruses that recently spread extensively in Asia and the US, shows in comparison a lower spatial extrapolation capacity than the HPAI H5N1 models, with a stronger association with intensively raised chicken densities and anthropogenic factors.","identifier":[{"type":"publisher-id","id":"19571"},{"type":"doi","id":"10.7554/eLife.19571"}],"date":{"day":"25","month":"11","year":"2016"},"license":"http://creativecommons.org/licenses/by/4.0/","path":"19571","entryfile":"elife-19571-v4.xml","files":["elife-19571-fig1-figsupp1-v2-600w.jpg","elife-19571-fig1-figsupp1-v3-600w.jpg","elife-19571-fig1-figsupp1-v4-600w.jpg","elife-19571-fig1-v2-600w.jpg","elife-19571-fig1-v3-600w.jpg","elife-19571-fig1-v4-600w.jpg","elife-19571-fig2-v2-600w.jpg","elife-19571-fig2-v3-600w.jpg","elife-19571-fig2-v4-600w.jpg","elife-19571-fig3-figsupp1-v2-600w.jpg","elife-19571-fig3-figsupp1-v3-600w.jpg","elife-19571-fig3-figsupp1-v4-600w.jpg","elife-19571-fig3-figsupp2-v2-600w.jpg","elife-19571-fig3-figsupp2-v3-600w.jpg","elife-19571-fig3-figsupp2-v4-600w.jpg","elife-19571-fig3-v2-600w.jpg","elife-19571-fig3-v3-600w.jpg","elife-19571-fig3-v4-600w.jpg","elife-19571-fig4-data1-v3-600w.jpg","elife-19571-fig4-data2-v3-600w.jpg","elife-19571-fig4-figsupp1-v2-600w.jpg","elife-19571-fig4-figsupp1-v3-600w.jpg","elife-19571-fig4-figsupp1-v4-600w.jpg","elife-19571-fig4-figsupp2-v2-600w.jpg","elife-19571-fig4-figsupp2-v3-600w.jpg","elife-19571-fig4-figsupp2-v4-600w.jpg","elife-19571-fig4-figsupp3-v2-600w.jpg","elife-19571-fig4-figsupp3-v3-600w.jpg","elife-19571-fig4-figsupp3-v4-600w.jpg","elife-19571-fig4-v2-600w.jpg","elife-19571-fig4-v3-600w.jpg","elife-19571-fig4-v4-600w.jpg","elife-19571-fig5-v2-600w.jpg","elife-19571-fig5-v3-600w.jpg","elife-19571-fig5-v4-600w.jpg","elife-19571-fig6-v2-600w.jpg","elife-19571-fig6-v3-600w.jpg","elife-19571-fig6-v4-600w.jpg","elife-19571-resp-fig1-v2-600w.jpg","elife-19571-resp-fig1-v3-600w.jpg","elife-19571-resp-fig1-v4-600w.jpg","elife-19571-resp-fig2-v2-600w.jpg","elife-19571-resp-fig2-v3-600w.jpg","elife-19571-resp-fig2-v4-600w.jpg","elife-19571-v1.xml","elife-19571-v2.xml","elife-19571-v3.xml"]}