{"title":"When 19 is greater than 92","author":[{"surname":"Zeitels","given-names":"Lauren R"},{"surname":"Mendell","given-names":"Joshua T"}],"abstract":"The gene <italic>miR-17-92</italic> encodes six different microRNAs, with one of these acting as an internal brake that opposes the oncogenic activity of the others in some cancer contexts.","identifier":[{"type":"publisher-id","id":"01514"},{"type":"doi","id":"10.7554/eLife.01514"}],"date":{"day":"15","month":"10","year":"2013"},"license":"http://creativecommons.org/licenses/by/3.0/","path":"01514","entryfile":"elife-01514-v1.xml","files":["elife-01514-fig1-v1-600w.jpg"]}