{"title":"What's new is older","author":[{"surname":"Rangel","given-names":"Lara M"},{"surname":"Eichenbaum","given-names":"Howard"}],"abstract":"Distinct populations of active cells in the dentate gyrus of the hippocampus may facilitate the unique encoding of changes in the environment.","identifier":[{"type":"publisher-id","id":"00605"},{"type":"doi","id":"10.7554/eLife.00605"}],"date":{"day":"20","month":"03","year":"2013"},"license":"http://creativecommons.org/licenses/by/3.0/","path":"00605","entryfile":"elife-00605-v1.xml","files":["elife-00605-fig1-v1-600w.jpg"]}