{"title":"From ions to insulin","author":[{"surname":"Kanelis","given-names":"Voula"}],"abstract":"Electron cryo-microscopy has revealed the three-dimensional structure of a potassium channel that has a central role in regulating the release of insulin from the pancreas.","identifier":[{"type":"publisher-id","id":"25159"},{"type":"doi","id":"10.7554/eLife.25159"}],"date":{"day":"09","month":"03","year":"2017"},"license":"http://creativecommons.org/licenses/by/4.0/","path":"25159","entryfile":"elife-25159-v2.xml","files":["elife-25159-fig1-v1-600w.jpg","elife-25159-fig1-v2-600w.jpg","elife-25159-v1.xml"]}