{"title":"Untwisting the <italic>Caenorhabditis elegans</italic> embryo","author":[{"surname":"Christensen","given-names":"Ryan Patrick"},{"surname":"Bokinsky","given-names":"Alexandra"},{"surname":"Santella","given-names":"Anthony"},{"surname":"Wu","given-names":"Yicong"},{"surname":"Marquina-Solis","given-names":"Javier"},{"surname":"Guo","given-names":"Min"},{"surname":"Kovacevic","given-names":"Ismar"},{"surname":"Kumar","given-names":"Abhishek"},{"surname":"Winter","given-names":"Peter W"},{"surname":"Tashakkori","given-names":"Nicole"},{"surname":"McCreedy","given-names":"Evan"},{"surname":"Liu","given-names":"Huafeng"},{"surname":"McAuliffe","given-names":"Matthew"},{"surname":"Mohler","given-names":"William"},{"surname":"Colón-Ramos","given-names":"Daniel A"},{"surname":"Bao","given-names":"Zhirong"},{"surname":"Shroff","given-names":"Hari"}],"abstract":"The nematode <italic>Caenorhabditis elegans</italic> possesses a simple embryonic nervous system with few enough neurons that the growth of each cell could be followed to provide a systems-level view of development. However, studies of single cell development have largely been conducted in fixed or pre-twitching live embryos, because of technical difficulties associated with embryo movement in late embryogenesis. We present open-source untwisting and annotation software (<ext-link>http://mipav.cit.nih.gov/plugin_jws/mipav_worm_plugin.php</ext-link>) that allows the investigation of neurodevelopmental events in late embryogenesis and apply it to track the 3D positions of seam cell nuclei, neurons, and neurites in multiple elongating embryos. We also provide a tutorial describing how to use the software (<xref>Supplementary file 1</xref>) and a detailed description of the untwisting algorithm (Appendix). The detailed positional information we obtained enabled us to develop a composite model showing movement of these cells and neurites in an 'average' worm embryo. The untwisting and cell tracking capabilities of our method provide a foundation on which to catalog <italic>C. elegans</italic> neurodevelopment, allowing interrogation of developmental events in previously inaccessible periods of embryogenesis.","identifier":[{"type":"publisher-id","id":"10070"},{"type":"doi","id":"10.7554/eLife.10070"}],"date":{"day":"03","month":"12","year":"2015"},"license":"http://creativecommons.org/publicdomain/zero/1.0/","path":"10070","entryfile":"elife-10070-v2.xml","files":["elife-10070-app1-fig1-v2-600w.jpg","elife-10070-app1-fig10-v2-600w.jpg","elife-10070-app1-fig11-v2-600w.jpg","elife-10070-app1-fig12-v2-600w.jpg","elife-10070-app1-fig13-v2-600w.jpg","elife-10070-app1-fig14-v2-600w.jpg","elife-10070-app1-fig15-v2-600w.jpg","elife-10070-app1-fig16-v2-600w.jpg","elife-10070-app1-fig17-v2-600w.jpg","elife-10070-app1-fig18-v2-600w.jpg","elife-10070-app1-fig2-v2-600w.jpg","elife-10070-app1-fig3-v2-600w.jpg","elife-10070-app1-fig4-v2-600w.jpg","elife-10070-app1-fig5-v2-600w.jpg","elife-10070-app1-fig6-v2-600w.jpg","elife-10070-app1-fig7-v2-600w.jpg","elife-10070-app1-fig8-v2-600w.jpg","elife-10070-app1-fig9-v2-600w.jpg","elife-10070-fig1-figsupp1-v2-600w.jpg","elife-10070-fig1-figsupp2-v2-600w.jpg","elife-10070-fig1-figsupp3-v2-600w.jpg","elife-10070-fig1-figsupp4-v2-600w.jpg","elife-10070-fig1-v2-600w.jpg","elife-10070-fig2-figsupp1-v2-600w.jpg","elife-10070-fig2-v2-600w.jpg","elife-10070-fig3-figsupp1-v2-600w.jpg","elife-10070-fig3-figsupp2-v2-600w.jpg","elife-10070-fig3-figsupp3-v2-600w.jpg","elife-10070-fig3-v2-600w.jpg","elife-10070-fig4-figsupp1-v2-600w.jpg","elife-10070-fig4-figsupp2-v2-600w.jpg","elife-10070-fig4-figsupp3-v2-600w.jpg","elife-10070-fig4-figsupp4-v2-600w.jpg","elife-10070-fig4-v2-600w.jpg","elife-10070-fig5-figsupp1-v2-600w.jpg","elife-10070-fig5-v2-600w.jpg","elife-10070-fig6-figsupp1-v2-600w.jpg","elife-10070-fig6-figsupp2-v2-600w.jpg","elife-10070-fig6-v2-600w.jpg","elife-10070-v1.xml"]}