{"title":"Developing cell biology","author":[{"surname":"Needleman","given-names":"Daniel"}],"abstract":"Experiments in <italic>Xenopus</italic> embryo extracts reveal that changes in cellular biochemistry cause mitotic spindles to decrease in size over the course of early development.","identifier":[{"type":"publisher-id","id":"00571"},{"type":"doi","id":"10.7554/eLife.00571"}],"date":{"day":"19","month":"02","year":"2013"},"license":"http://creativecommons.org/licenses/by/3.0/","path":"00571","entryfile":"elife-00571-v1.xml","files":["elife-00571-fig1-v1-600w.jpg"]}