{"title":"To freeze or not to freeze","author":[{"surname":"Bangasser","given-names":"Debra"}],"abstract":"Male and female rats respond to a fearful experience in different ways, but this was not previously taken into account in research into psychiatric disorders.","identifier":[{"type":"publisher-id","id":"13119"},{"type":"doi","id":"10.7554/eLife.13119"}],"date":{"day":"23","month":"12","year":"2015"},"license":"http://creativecommons.org/licenses/by/4.0/","path":"13119","entryfile":"elife-13119-v1.xml","files":[]}