{"title":"Correction: Natural epigenetic polymorphisms lead to intraspecific variation in Arabidopsis gene imprinting","author":[{"surname":"Pignatta","given-names":"Daniela"},{"surname":"Erdmann","given-names":"Robert M"},{"surname":"Scheer","given-names":"Elias"},{"surname":"Picard","given-names":"Colette L"},{"surname":"Bell","given-names":"George W"},{"surname":"Gehring","given-names":"Mary"}],"abstract":null,"identifier":[{"type":"publisher-id","id":"08658"},{"type":"doi","id":"10.7554/eLife.08658"}],"date":{"day":"18","month":"05","year":"2015"},"license":"http://creativecommons.org/licenses/by/4.0/","path":"08658","entryfile":"elife-08658-v1.xml","files":[]}