{"title":"Correction: Tissue acidosis induces neuronal necroptosis via ASIC1a channel independent of its ionic conduction","author":[{"surname":"Wang","given-names":"Yi-Zhi"},{"surname":"Wang","given-names":"Jing-Jing"},{"surname":"Huang","given-names":"Yu"},{"surname":"Liu","given-names":"Fan"},{"surname":"Zeng","given-names":"Wei-Zheng"},{"surname":"Li","given-names":"Ying"},{"surname":"Xiong","given-names":"Zhi-Gang"},{"surname":"Zhu","given-names":"Michael X"},{"surname":"Xu","given-names":"Tian-Le"}],"abstract":null,"identifier":[{"type":"publisher-id","id":"14128"},{"type":"doi","id":"10.7554/eLife.14128"}],"date":{"day":"22","month":"01","year":"2016"},"license":"http://creativecommons.org/licenses/by/4.0/","path":"14128","entryfile":"elife-14128-v1.xml","files":["elife-14128-fig1-v1-600w.jpg","elife-14128-fig2-v1-600w.jpg"]}